wsrequests
