Metadata-Version: 1.0
Name: wsrequests
Version: 0.1.1
Summary: thin wrapper for requests enable websocket
Home-page: https://github.com/denzow/wsrequests
Author: denzow
Author-email: denzow@gmail.com
License: MIT License
